photo_burst_detection/__init__.py
photo_burst_detection/__main__.py
photo_burst_detection/auth.py
photo_burst_detection/conf.py
photo_burst_detection/scan.py
photo_burst_detection/views.py
photo_burst_detection/static/favicon.svg
photo_burst_detection/static/style.css
photo_burst_detection/templates/burst.html
photo_burst_detection/templates/change_root.html
photo_burst_detection/templates/folder.html
photo_burst_detection/templates/index.html
photo_burst_detection/templates/layout.html
photo_burst_detection/templates/login.html
photo_burst_detection/templates/naming.html
photo_burst_detection-1.4.3.dist-info/METADATA
photo_burst_detection-1.4.3.dist-info/WHEEL
photo_burst_detection-1.4.3.dist-info/top_level.txt
photo_burst_detection-1.4.3.dist-info/RECORD
