Metadata-Version: 2.1
Name: photo_burst_detection
Version: 1.4.3
Summary: Flask App for photo burst detection
Home-page: https://gitlab.com/batou9150/photo_burst_detection
Author: batou9150
Classifier: Programming Language :: Python :: 3
Classifier: Operating System :: OS Independent
Requires-Python: >=3.6
Requires-Dist: flask
Requires-Dist: flask-login
Requires-Dist: flask-ldap3-login
